Metadata-Version: 1.0
Name: GB-distributions-test1
Version: 0.0
Summary: Gaussian and Bionomial distributions
Home-page: UNKNOWN
Author: Ayyoub Rezaeian
Author-email: ayyoub.rezaeian@gmail.com
License: UNKNOWN
Platform: UNKNOWN
